[{"id":"20bf399a-4a95-4952-ad5f-2c4d814fb413","title":"ABSOLUTE CINEMA","content":"HAHAHAHAHA SABI NI MAMA SO SO 😍 SO 😍 SO 😍 A SO THE SO THE THE SO 😍 SO 😍 A QUESTION 🤔 THE THE SO THE THE SO SO 😍 SO THE WORLD THE THE SO SO THE THE SO THE THE WORLD THE THE WORLD 🌎 SO 😍 A QUESTION YOU SO SO 😍 SO 😍 A SO SO 😍 SO THE WORLD THE WORLD THE THE WORLD THE WORLD THE WORLD THE WORLD THE THE THE WORLD 🌎 EVERYTHING IS JMAFK TESTING TO SO 😍","timestamp":1756789692585,"author":"admin","imageUrl":"https://raw.githubusercontent.com/JesmerAFK/mc-share/main/images/posts/post_image_20250902_130811.jpg"}]